LICENSE
MANIFEST.in
NEWS
setup.py
db/monitor.sql
mimir/__init__.py
mimir.egg-info/PKG-INFO
mimir.egg-info/SOURCES.txt
mimir.egg-info/dependency_links.txt
mimir.egg-info/not-zip-safe
mimir.egg-info/requires.txt
mimir.egg-info/top_level.txt
mimir/aggregator/__init__.py
mimir/aggregator/aggregator.py
mimir/aggregator/fetcher.py
mimir/aggregator/tap.py
mimir/aggregator/writer.py
mimir/aggregator/test/__init__.py
mimir/aggregator/test/test_aggregator.py
mimir/monitor/__init__.py
mimir/monitor/news.py
mimir/monitor/presence.py
mimir/monitor/tap.py
twisted/plugins/dropin.cache
twisted/plugins/mimir_aggregator.py
twisted/plugins/mimir_aggregator.pyc
twisted/plugins/mimir_monitor.py
twisted/plugins/mimir_monitor.pyc