Metadata-Version: 1.0
Name: mimir
Version: 0.6.3
Summary: Mimir daemons
Home-page: http://mimir.ik.nu/
Author: Ralph Meijer
Author-email: ralphm@ik.nu
License: MIT
Platform: UNKNOWN
